pylsd2/__init__.py
pylsd2/wrapper.py
pylsd2/bindings/__init__.py
pylsd2/bindings/fn_types.py
pylsd2/bindings/lsd_ctypes.py
pylsd2/lib/linux/libEDLines.so
pylsd2/lib/linux/liblsd.so
pylsd2/lib/win32/x64/EDLines.dll
pylsd2/lib/win32/x64/lsd.dll
pylsd2/lib/win32/x86/EDLines.dll
pylsd2/lib/win32/x86/lsd.dll
pylsd2-0.0.3.dist-info/LICENSE
pylsd2-0.0.3.dist-info/METADATA
pylsd2-0.0.3.dist-info/WHEEL
pylsd2-0.0.3.dist-info/top_level.txt
pylsd2-0.0.3.dist-info/RECORD
